README.rst
setup.py
kleverklog/__init__.py
kleverklog/kleverklog.py
kleverklog/python_logging.py
kleverklog/twisted_logger.py
kleverklog.egg-info/PKG-INFO
kleverklog.egg-info/SOURCES.txt
kleverklog.egg-info/dependency_links.txt
kleverklog.egg-info/entry_points.txt
kleverklog.egg-info/requires.txt
kleverklog.egg-info/top_level.txt