Metadata-Version: 1.1
Name: kleverklog
Version: 0.2.0
Summary: Klever KLog uses Apache Kafka to store your program log and provides a Kafka client to search, filter and navigate your logs.
Home-page: https://github.com/patrickfournier/kleverklog
Author: Patrick Fournier
Author-email: patrick@patrickfournier.com
License: Apache
Keywords: kafka logging development twisted
Platform: UNKNOWN
Classifier: Development Status :: 4 - Beta
Classifier: Intended Audience :: Developers
Classifier: Topic :: Software Development
Classifier: License :: OSI Approved :: Apache Software License
Classifier: Programming Language :: Python :: 2
Classifier: Programming Language :: Python :: 2.7
